alibabacloud_hitsdb20170601/__init__.py
alibabacloud_hitsdb20170601/client.py
alibabacloud_hitsdb20170601/models.py
alibabacloud_hitsdb20170601_py2-1.0.0.dist-info/LICENSE
alibabacloud_hitsdb20170601_py2-1.0.0.dist-info/METADATA
alibabacloud_hitsdb20170601_py2-1.0.0.dist-info/WHEEL
alibabacloud_hitsdb20170601_py2-1.0.0.dist-info/top_level.txt
alibabacloud_hitsdb20170601_py2-1.0.0.dist-info/RECORD
